Workbook

Sheet Leia-me
A1: Planilhas de apoio ao dossie de auditoria - SABESP 2025
A2: Davi Fernandes Bonfim - Matricula 241003473 - Auditoria 1 (UnB, CCA0024, Turma 02). Valores em R$ mil, salvo indicacao.
A4: Fonte dos dados reais: DFP 2025 e 2024 da SABESP (CVM). Dados da base e da amostra sao SINTETICOS.
A5: Celulas em azul sao entradas (editaveis); as demais sao formulas. A coluna "Fonte" cita a pagina do PDF da DFP 2025 (F1).
A6: Abas: Materialidade (PT 320); Conciliacoes (PT 500); Analiticos (PT 520); Sensibilidade (PT 540); Amostragem (PT 530); Amostra (PT 530);
A7: Conc_Base (T-01); Erros (comparacao dos erros inseridos com os identificados); Distorcoes (PT 450).
A8: Premissas hardcoded estao identificadas ao lado de cada tabela. Nada aqui e opiniao de auditoria independente.

Sheet Materialidade
A1: PT 320 - Materialidade
A2: R$ mil, DFP 2025 consolidada (F1, pp. 24-28)
A4: Base de referencia | B4: Valor 2025 | C4: Percentual | D4: Materialidade resultante | E4: Papel | F4: Fonte
A5: Lucro antes dos tributos (LAIR) | B5: 11701851 | C5: 0.05 | D5: =B5*C5 -> 585092.55 | E5: Adotado | F5: F1, p. 28
A6: Receita liquida | B6: 38092050 | C6: 0.01 | D6: =B6*C6 -> 380920.5 | E6: Referencia | F6: F1, p. 28
A7: Ativo total | B7: 104202767 | C7: 0.005 | D7: =B7*C7 -> 521013.84 | E7: Referencia | F7: F1, p. 24
A8: Patrimonio liquido | B8: 42401124 | C8: 0.01 | D8: =B8*C8 -> 424011.24 | E8: Referencia | F8: F1, p. 27
A11: Parametro | B11: Valor | C11: Premissa | D11: Calculo
A12: Materialidade global (MG) | B12: =ROUND(D5,0) -> 585093 | C12: 5% do LAIR
A13: Percentual da ME sobre a MG | B13: 0.7 | C13: Julgamento do aluno: auditoria inicial e riscos significativos
A14: Materialidade para execucao (ME) | B14: =ROUND(B12*B13,0) -> 409565
A15: Percentual do limite de distorcoes triviais | B15: 0.05 | C15: 5% da MG
A16: Limite de distorcoes claramente triviais | B16: =ROUND(B12*B15,0) -> 29255
A17: Percentual da materialidade especifica (partes relacionadas) | B17: 0.5
A18: Materialidade especifica - partes relacionadas | B18: =ROUND(B12*B17,0) -> 292547
A19: Limite de investigacao analitica (25% da ME) | B19: =ROUND(B14*0.25,0) -> 102391 | C19: Premissa do aluno para riscos significativos
A20: MG como % da receita | B20: =B12/B6 -> 0.015359977
A21: MG como % do ativo | B21: =B12/B7 -> 0.0056149469

Sheet Conciliacoes
A1: PT 500 - Conciliacoes (R$ mil, consolidado)
A2: Entradas em azul vem das notas da DFP 2025 (F1); diferenca deve ser zero
A4: Conciliacao | B4: Comp. 1 | C4: Comp. 2 | D4: Comp. 3 | E4: Comp. 4 | F4: Comp. 5 | G4: Comp. 6 | H4: Calculado | I4: Saldo nas demonstracoes | J4: Diferenca | K4: Fonte
A5: Intangivel: saldo inicial + movimentos | B5: 44771124 | C5: 3207 | D5: 8117869 | E5: -139884 | F5: -98731 | G5: -2161112 | H5: =SUM(B5:G5) -> 50492473 | I5: 50492473 | J5: =H5-I5 -> 0 | K5: Nota 14, p. 73; balanco p. 25
A6: Intangivel: soma das classes | B6: 137725 | C6: 75089 | D6: 3730121 | E6: 45946471 | F6: 551102 | G6: 51965 | H6: =SUM(B6:G6) -> 50492473 | I6: 50492473 | J6: =H6-I6 -> 0 | K6: Nota 14, p. 72
A7: Ativo de contrato: saldo inicial + movimentos | B7: 4877667 | C7: 16684564 | D7: -62684 | E7: 24108 | F7: -8117869 | G7: -2387270 | H7: =SUM(B7:G7) -> 11018516 | I7: 11018516 | J7: =H7-I7 -> 0 | K7: Nota 13, p. 69; balanco p. 24
A8: Ativo financeiro: saldo inicial + movimentos | B8: 17601626 | C8: 2387270 | D8: 1676434 | H8: =SUM(B8:G8) -> 21665330 | I8: 21665330 | J8: =H8-I8 -> 0 | K8: Nota 15, p. 79
A9: Receita liquida pela Nota 30 | B9: 24761056 | C9: 14437363 | D9: -966169 | E9: 1676434 | F9: -1702667 | G9: -113967 | H9: =SUM(B9:G9) -> 38092050 | I9: 38092050 | J9: =H9-I9 -> 0 | K9: Nota 30, p. 131; DRE p. 28
A10: Receita liquida pela nota de segmentos | B10: 25471321 | C10: 14437363 | D10: -1816634 | H10: =SUM(B10:G10) -> 38092050 | I10: 38092050 | J10: =H10-I10 -> 0 | K10: p. 130
A11: Ativo total: circulante + nao circulante | B11: 18556510 | C11: 85646257 | H11: =SUM(B11:G11) -> 104202767 | I11: 104202767 | J11: =H11-I11 -> 0 | K11: Balanco p. 24
A12: Passivo total: circ. + nao circ. + PL | B12: 16552914 | C12: 45248729 | D12: 42401124 | H12: =SUM(B12:G12) -> 104202767 | I12: 104202767 | J12: =H12-I12 -> 0 | K12: Balanco pp. 26-27
A13: Lucro liquido: LAIR - IR e CSLL | B13: 11701851 | C13: -3239792 | H13: =SUM(B13:G13) -> 8462059 | I13: 8462059 | J13: =H13-I13 -> 0 | K13: DRE p. 28
A14: Variacao de caixa: FCO + investimento + financiamento | B14: 8361115 | C14: -15703622 | D14: 10323127 | H14: =SUM(B14:G14) -> 2980620 | I14: 2980620 | J14: =H14-I14 -> 0 | K14: DFC
A15: Caixa final: saldo inicial + variacao | B15: 1682606 | C15: 2980620 | H15: =SUM(B15:G15) -> 4663226 | I15: 4663226 | J15: =H15-I15 -> 0 | K15: Balanco p. 24
A16: Divida liquida: emprestimos - caixa - aplicacoes | B16: 40142347 | C16: -4663226 | D16: -7707745 | H16: =SUM(B16:G16) -> 27771376 | I16: 27771376 | J16: =H16-I16 -> 0 | K16: Nota 5, p. 55
A17: Provisoes judiciais liquidas por tipo | B17: 132901 | C17: 51282 | D17: 153711 | E17: 11590 | F17: 1393402 | G17: 160526 | H17: =SUM(B17:G17) -> 1903412 | I17: 1903412 | J17: =H17-I17 -> 0 | K17: Nota 23, p. 110
A19: Total de diferencas absolutas | J19: =SUMPRODUCT(ABS(J5:J17)) -> 0

Sheet Analiticos
A1: PT 520 - Procedimentos analiticos (R$ mil)
A2: IPCA 2025 = 4,26% (IBGE, F6). Limite de investigacao vem da aba Materialidade.
A3: IPCA 2025 | B3: 0.0426 | C3: Limite de investigacao | D3: =Materialidade!B19 -> 102391
A5: Analitico | B5: Base 1 | C5: Base 2 | D5: Registrado | E5: Esperado | F5: Diferenca | G5: Acima do limite? | H5: Metodo / premissa
A6: A1. Receita bruta de saneamento | B6: 23894855 | D6: 24761056 | E6: =B6*(1+$B$3) -> 24912776 | F6: =D6-E6 -> -151719.82 | G6: =IF(ABS(F6)>$D$3,"Sim","Nao") -> Sim | H6: Valor de 2024 x (1 + IPCA)
A7: A2. Atualizacao do ativo financeiro | B7: 17601626 | C7: 2387270 | D7: 1676434 | E7: =B7*$B$3+C7*$B$3/2 -> 800678.12 | F7: =D7-E7 -> 875755.88 | G7: =IF(ABS(F7)>$D$3,"Sim","Nao") -> Sim | H7: Saldo inicial x IPCA + metade das transferencias x IPCA
A8: A3. Amortizacao do intangivel da URAE-1 | B8: 911134 | D8: 1765919 | E8: =B8*2 -> 1822268 | F8: =D8-E8 -> -56349 | G8: =IF(ABS(F8)>$D$3,"Sim","Nao") -> Nao | H8: Amortizacao do 2o semestre de 2024 x 2
A9: A4. IR e CSLL | B9: 11701851 | C9: 48153 | D9: 3239792 | E9: =0.34*(B9-C9)-0.34*1800000 -> 3350257.3 | F9: =D9-E9 -> -110465.32 | G9: =IF(ABS(F9)>$D$3,"Sim","Nao") -> Sim | H9: 34% x (LAIR - equivalencia) - 34% x JCP de R$ 1,8 bi (suposicao do aluno)
A10: A5. PECLD | B10: 557789 | C10: 23894855 | D10: 62067 | E10: =B10/C10*D6 -> 578009.14 | F10: =D10-E10 -> -515942.14 | G10: =IF(ABS(F10)>$D$3,"Sim","Nao") -> Sim | H10: Percentual de 2024 sobre receita bruta x receita bruta de 2025
A11: A6. Despesas administrativas | B11: 2311438 | D11: 1018282 | E11: =B11*(1+$B$3) -> 2409905.3 | F11: =D11-E11 -> -1391623.3 | G11: =IF(ABS(F11)>$D$3,"Sim","Nao") -> Sim | H11: Valor de 2024 x (1 + IPCA)
A13: Reconciliacao da PECLD (Nota 10c, p. 60): baixas - recuperacoes - reversoes (2) = despesa
A14: Componentes | B14: 501786 | C14: -401667 | D14: -29099 | E14: -8953 | F14: =SUM(B14:E14) -> 62067 | G14: =F14-D10 -> 0 | H14: Diferenca para a PECLD registrada

Sheet Sensibilidade
A1: PT 540 - Sensibilidade do ativo financeiro (R$ mil)
A2: Saldo (Nota 15, F1 p. 79). Premissas variaveis em azul.
A4: Saldo inicial | B4: 17601626
A5: Transferencias do ano | B5: 2387270
A6: Saldo final | B6: 21665330
A7: Base de atualizacao | B7: =B4+B5/2 -> 18795261
A8: Efeito divulgado da mudanca de estimativa (p. 80) | B8: 1000000
A10: Premissa variada | B10: Variacao | C10: Efeito | D10: % da MG | E10: % da ME | F10: Faixa
A11: IPCA +/- 1 ponto percentual | B11: 0.01 | C11: =B7*B11 -> 187952.61 | D11: =C11/Materialidade!$B$12 -> 0.32123544 | E11: =C11/Materialidade!$B$14 -> 0.45890789 | F11: =IF(C11>=Materialidade!$B$14,"Acima da ME",IF(C11>=Materialidade!$B$12*0.5,"Entre 50% da MG e a ME","Abaixo")) -> Abaixo
A12: Alcance da majoracao de PIS e Cofins +/- 25% | B12: 0.25 | C12: =B8*B12 -> 250000 | D12: =C12/Materialidade!$B$12 -> 0.4272825 | E12: =C12/Materialidade!$B$14 -> 0.61040372 | F12: =IF(C12>=Materialidade!$B$14,"Acima da ME",IF(C12>=Materialidade!$B$12*0.5,"Entre 50% da MG e a ME","Abaixo")) -> Abaixo
A13: Base de ativos reversiveis +/- 5% | B13: 0.05 | C13: =B6*B13 -> 1083266.5 | D13: =C13/Materialidade!$B$12 -> 1.8514433 | E13: =C13/Materialidade!$B$14 -> 2.6449196 | F13: =IF(C13>=Materialidade!$B$14,"Acima da ME",IF(C13>=Materialidade!$B$12*0.5,"Entre 50% da MG e a ME","Abaixo")) -> Acima da ME
A14: Base de ativos reversiveis +/- 1% | B14: 0.01 | C14: =B6*B14 -> 216653.3 | D14: =C14/Materialidade!$B$12 -> 0.37028865 | E14: =C14/Materialidade!$B$14 -> 0.52898392 | F14: =IF(C14>=Materialidade!$B$14,"Acima da ME",IF(C14>=Materialidade!$B$12*0.5,"Entre 50% da MG e a ME","Abaixo")) -> Abaixo

Sheet Amostragem
A1: PT 530 - Amostragem por unidade monetaria (MUS), base SINTETICA
A2: Parametros editaveis em azul; resultados da execucao do script 03 (valores em R$ mil).
A4: Populacao (valor liquido registrado) | B4: 50492473
A5: Distorcao toleravel (= ME) | B5: =Materialidade!B14 -> 409565
A6: Fator de confianca (95%, zero erros) | B6: 3
A7: Fator de expansao (95%) | B7: 1.6
A8: Distorcao esperada | B8: 40000
A9: Intervalo de amostragem = (TM - EM x FE) / FC | B9: =(B5-B8*B7)/B6 -> 115188.33
A10: Tamanho esperado = populacao / intervalo | B10: =B4/B9 -> 438.34711
A11: Precisao basica = FC x intervalo | B11: =B6*B9 -> 345565
A13: Resultados da execucao (script 03; semente 241003473)
A14: Itens-chave (valor >= intervalo) | B14: 1
A15: Itens por MUS | B15: 438
A16: Total de itens testados | B16: 439
A17: Itens com distorcao | B17: 3
A18: Distorcao projetada (mais provavel) | B18: 27187.2
A19: Limite superior de distorcao (Stringer) | B19: 362072.3
A20: Distorcao real inserida na base (verdade de terreno) | B20: 135634.6
A22: Limite superior < distorcao toleravel? | B22: =IF(B19<B5,"Sim","Nao") -> Sim
A23: Distorcao projetada / distorcao real | B23: =B18/B20 -> 0.20044443

Sheet Amostra
A1: PT 530 - Itens selecionados e resultado do teste (SIMULADO)
A2: Valor correto vem da verdade de terreno sintetica; distorcao e taint sao formulas.
A4: id_unidade | B4: Classe | C4: Tipo | D4: Municipio (sintetico) | E4: Selecao | F4: Valor registrado (mil) | G4: Valor correto (mil) | H4: Distorcao (mil) | I4: Taint (MUS)
A5: U0071262 | B5: Contratos de Concessao URAE-1 | C5: ETE | D5: MUN-104 | E5: ITEM-CHAVE (>= intervalo) | F5: 119367.12 | G5: 119367.12 | H5: =F5-G5 -> 0 | I5: =IF(E5="MUS",H5/F5,"")
A6: U0000160 | B6: Contratos de Concessao URAE-1 | C6: ETE | D6: MUN-020 | E6: MUS | F6: 11034.726 | G6: 11034.726 | H6: =F6-G6 -> 0 | I6: =IF(E6="MUS",H6/F6,"") -> 0
A7: U0001456 | B7: Contratos de Concessao URAE-1 | C7: ETE | D7: MUN-169 | E7: MUS | F7: 8420.907 | G7: 8420.907 | H7: =F7-G7 -> 0 | I7: =IF(E7="MUS",H7/F7,"") -> 0
A8: U0002776 | B8: Contratos de Concessao URAE-1 | C8: ETE | D8: MUN-113 | E8: MUS | F8: 12549.861 | G8: 12549.861 | H8: =F8-G8 -> 0 | I8: =IF(E8="MUS",H8/F8,"") -> 0
A9: U0003881 | B9: Contratos de Concessao URAE-1 | C9: ESTACAO_ELEVATORIA | D9: MUN-252 | E9: MUS | F9: 171.061 | G9: 171.061 | H9: =F9-G9 -> 0 | I9: =IF(E9="MUS",H9/F9,"") -> 0
A10: U0005092 | B10: Contratos de Concessao URAE-1 | C10: ETE | D10: MUN-098 | E10: MUS | F10: 16144.003 | G10: 16144.003 | H10: =F10-G10 -> 0 | I10: =IF(E10="MUS",H10/F10,"") -> 0
A11: U0006513 | B11: Contratos de Concessao URAE-1 | C11: RESERVATORIO | D11: MUN-272 | E11: MUS | F11: 4523.6 | G11: 4523.6 | H11: =F11-G11 -> 0 | I11: =IF(E11="MUS",H11/F11,"") -> 0
A12: U0007865 | B12: Contratos de Concessao URAE-1 | C12: REDE_ESGOTO | D12: MUN-277 | E12: MUS | F12: 7.436 | G12: 7.436 | H12: =F12-G12 -> 0 | I12: =IF(E12="MUS",H12/F12,"") -> 0
A13: U0008773 | B13: Contratos de Concessao URAE-1 | C13: EQUIPAMENTO_OPERACIONAL | D13: MUN-009 | E13: MUS | F13: 668.572 | G13: 668.572 | H13: =F13-G13 -> 0 | I13: =IF(E13="MUS",H13/F13,"") -> 0
A14: U0009418 | B14: Contratos de Concessao URAE-1 | C14: ETE | D14: MUN-056 | E14: MUS | F14: 8585.872 | G14: 8585.872 | H14: =F14-G14 -> 0 | I14: =IF(E14="MUS",H14/F14,"") -> 0
A15: U0010404 | B15: Contratos de Concessao URAE-1 | C15: ESTACAO_ELEVATORIA | D15: MUN-165 | E15: MUS | F15: 2511.867 | G15: 2511.867 | H15: =F15-G15 -> 0 | I15: =IF(E15="MUS",H15/F15,"") -> 0
A16: U0011812 | B16: Contratos de Concessao URAE-1 | C16: ESTACAO_ELEVATORIA | D16: MUN-271 | E16: MUS | F16: 6633.783 | G16: 6633.783 | H16: =F16-G16 -> 0 | I16: =IF(E16="MUS",H16/F16,"") -> 0
... A443: U0519844 | B443: Contratos de Concessao URAE-1 | C443: REDE_ESGOTO | D443: MUN-011 | E443: MUS | F443: 211.354 | G443: 211.354 | H443: =F443-G443 -> 0 | I443: =IF(E443="MUS",H443/F443,"") -> 0
A445: Total de distorcao nos itens | H445: =SUM(H5:H443) -> 81.573

Sheet Conc_Base
A1: T-01 - Conciliacao da base sintetica com a Nota 14 (R$ mil)
A2: Base = soma da base sintetica; Nota 14 = F1, p. 72
A4: Classe | B4: Custo - base | C4: Custo - Nota 14 | D4: Amort. - base | E4: Amort. - Nota 14 | F4: VL - base | G4: VL - Nota 14 | H4: Dif. VL
A5: Contratos de Concessao URAE-1 | B5: 69281545 | C5: 69281545 | D5: 23335074 | E5: 23335074 | F5: 45946471 | G5: 45946471 | H5: =F5-G5 -> 0
A6: Compromissos de Contratos | B6: 4437857 | C6: 4437857 | D6: 707736 | E6: 707736 | F6: 3730121 | G6: 3730121 | H6: =F6-G6 -> 0
A7: Licenca de uso de software | B7: 1696773 | C7: 1696773 | D7: 1145671 | E7: 1145671 | F7: 551102 | G7: 551102 | H7: =F7-G7 -> 0
A8: Direito de uso - Outros ativos | B8: 240646 | C8: 240646 | D8: 188681 | E8: 188681 | F8: 51965 | G8: 51965 | H8: =F8-G8 -> 0
A9: Contratos de concessao - outros | B9: 135470 | C9: 135470 | D9: 60381 | E9: 60381 | F9: 75089 | G9: 75089 | H9: =F9-G9 -> 0
A10: Contratos de concessao - novos contratos | B10: 148000 | C10: 148000 | D10: 10275 | E10: 10275 | F10: 137725 | G10: 137725 | H10: =F10-G10 -> 0
A11: TOTAL | B11: =SUM(B5:B10) -> 75940291 | C11: =SUM(C5:C10) -> 75940291 | D11: =SUM(D5:D10) -> 25447818 | E11: =SUM(E5:E10) -> 25447818 | F11: =SUM(F5:F10) -> 50492473 | G11: =SUM(G5:G10) -> 50492473 | H11: =F11-G11 -> 0

Sheet Erros
A1: Erros inseridos x erros identificados pelos testes
A2: Base SINTETICA; verdade de terreno em dados/registro_erros_inseridos.csv
A4: Codigo | B4: Teste | C4: Inseridas | D4: Identificadas | E4: Verdadeiros positivos | F4: Falsos positivos | G4: Falsos negativos | H4: Precisao | I4: Cobertura | J4: Distorcao inserida (mil) | K4: Distorcao identificada (mil)
A5: S-01 | B5: T-04 | C5: 45 | D5: 45 | E5: 45 | F5: =D5-E5 -> 0 | G5: =C5-E5 -> 0 | H5: =E5/D5 -> 1 | I5: =E5/C5 -> 1 | J5: 61000 | K5: 61000
A6: S-02 | B6: T-05 (estagio 2) | C6: 160 | D6: 160 | E6: 160 | F6: =D6-E6 -> 0 | G6: =C6-E6 -> 0 | H6: =E6/D6 -> 1 | I6: =E6/C6 -> 1 | J6: 38000 | K6: 38000
A7: S-03 | B7: T-06 | C7: 1400 | D7: 1400 | E7: 1400 | F7: =D7-E7 -> 0 | G7: =C7-E7 -> 0 | H7: =E7/D7 -> 1 | I7: =E7/C7 -> 1 | J7: 24088.1 | K7: 24088.1
A8: S-04 | B8: T-03 | C8: 126 | D8: 126 | E8: 126 | F8: =D8-E8 -> 0 | G8: =C8-E8 -> 0 | H8: =E8/D8 -> 1 | I8: =E8/C8 -> 1 | J8: 12546.5 | K8: 12546.5
A9: Total | C9: =SUM(C5:C8) -> 1731 | D9: =SUM(D5:D8) -> 1731 | E9: =SUM(E5:E8) -> 1731 | F9: =SUM(F5:F8) -> 0 | G9: =SUM(G5:G8) -> 0 | J9: =SUM(J5:J8) -> 135634.6 | K9: =SUM(K5:K8) -> 135634.6
A11: Nota: T-05 estagio 1 (automatico) listou 360 unidades, das quais 200 eram falsos positivos (ampliacao de capacidade apos manutencao) resolvidos pela leitura do texto.

Sheet Distorcoes
A1: PT 450 - Mapa de distorcoes (SINTETICAS), R$ mil
A2: S-01 a S-04 inseridas e confirmadas pelos testes; S-05 e julgamental, fora da base (PT 540), valor sintetico
A4: Cod. | B4: Descricao | C4: Tipo | D4: Valor | E4: Situacao | F4: Fonte do valor
A5: S-01 | B5: Corte: obras de jan/2026 capitalizadas em dez/2025 | C5: Fato | D5: 61000 | E5: Nao corrigida | F5: Base sintetica (T-04)
A6: S-02 | B6: Classificacao: manutencao capitalizada | C6: Fato | D6: 38000 | E6: Nao corrigida | F6: Base sintetica (T-05)
A7: S-03 | B7: Amortizacao: vida util registrada maior que a padrao | C7: Fato | D7: 24088.1 | E7: Corrigida | F7: Base sintetica (T-06)
A8: S-04 | B8: Duplicidade de unidades | C8: Fato | D8: 12546.5 | E8: Corrigida | F8: Base sintetica (T-03)
A9: S-05 | B9: Estimativa do ativo financeiro: premissa x faixa do auditor | C9: Julgamento | D9: 105000 | E9: Nao corrigida | F9: Valor sintetico provisorio (fora da base)
A11: Corrigidas | D11: =SUMIF(E5:E9,"Corrigida",D5:D9) -> 36634.6 | E11: =D11/Materialidade!B12 -> 0.062613294
A12: Nao corrigidas (agregado) | D12: =SUMIF(E5:E9,"Nao corrigida",D5:D9) -> 204000 | E12: =D12/Materialidade!B12 -> 0.34866252 | F12: % da MG
A13: Nao corrigidas / ME | D13: =D12/Materialidade!B14 -> 0.49808944
A14: Nao corrigidas / LAIR | D14: =D12/Materialidade!B5 -> 0.017433139
A15: Itens acima do limite trivial | D15: =COUNTIF(D5:D9,">"&Materialidade!B16) -> 3
